imagines/VERSION
imagines/__init__.py
imagines/core.py
imagines/version.py
imagines-0.0.7.2.dist-info/LICENSE
imagines-0.0.7.2.dist-info/METADATA
imagines-0.0.7.2.dist-info/WHEEL
imagines-0.0.7.2.dist-info/top_level.txt
imagines-0.0.7.2.dist-info/RECORD
