Metadata-Version: 2.1
Name: imagines
Version: 0.0.7.2
Summary: ImagineS (Image Engine Search) tool augments an image dataset by searching a series of queries in Google Images.
Home-page: https://github.com/ugm2/ImagineS
Author: Unai Garay
Author-email: unaigaraymaestre@gmail.com
License: UNKNOWN
Platform: UNKNOWN
Classifier: Programming Language :: Python :: 3
Classifier: License :: OSI Approved :: MIT License
Classifier: Operating System :: OS Independent
Requires-Python: >=3.7
License-File: LICENSE
Requires-Dist: selenium (>=4.1.0)
Requires-Dist: pillow (>=8.3.1)
Requires-Dist: tqdm (>=4.62.3)
Requires-Dist: webdriver-manager (>=3.7.0)
